[
    {
        "title": "Evaluating Market Structures in Developing Nations",
        "category": "Micro Economics",
        "date": "June 2026",
        "description": "An analysis of foundational micro-economic behavior traversing local markets and global shocks.",
        "image": "https://source.unsplash.com/600x400/?finance,chart",
        "link": "#"
    },
    {
        "title": "Inflationary Adjustments Post-2025",
        "category": "Macro Economics",
        "date": "July 2026",
        "description": "Comprehensive review of systematic shifts impacting gross regional products and global trade metrics.",
        "image": "https://source.unsplash.com/600x400/?data,market",
        "link": "#"
    }
]
